Workbook

Sheet Simulador FII
A1: SIMULADOR DE INVESTIMENTOS EM FUNDOS IMOBILIÁRIOS
A3: DADOS DA SIMULAÇÃO | D3: RESULTADOS
A4: Salário mensal | B4: 5000 | D4: Total investido | E4: =B7+(B6*B8*12)
A5: Percentual sugerido para investir | B5: 0.3 | D5: Patrimônio acumulado | E5: =FV(B9,B8*12,-B6,-B7,0)
A6: Aporte mensal | B6: =B4*B5 | D6: Rendimento mensal estimado | E6: =E5*B9
A7: Investimento inicial | B7: 1000 | D7: Dividendos estimados por mês | E7: =E6
A8: Prazo (anos) | B8: 10 | D8: Lucro estimado | E8: =E5-E4
A9: Taxa de rendimento mensal | B9: 0.008
A10: Perfil do investidor | B10: Moderado
A12: CENÁRIOS DE INVESTIMENTO | F12: DISTRIBUIÇÃO POR PERFIL
A13: Prazo | B13: Total Investido | C13: Patrimônio Acumulado | D13: Dividendos Mensais Estimados | F13: Tipo de FII | G13: % | H13: Valor Mensal
A14: 2 | B14: =$B$7+($B$6*A14*12) | C14: =FV($B$9,A14*12,-$B$6,-$B$7,0) | D14: =C14*$B$9 | F14: =Perfis!A4 | G14: =INDEX(Perfis!$B$4:$D$9,MATCH(F14,Perfis!$A$4:$A$9,0),MATCH($B$10,Perfis!$B$3:$D$3,0)) | H14: =$B$6*G14
A15: 5 | B15: =$B$7+($B$6*A15*12) | C15: =FV($B$9,A15*12,-$B$6,-$B$7,0) | D15: =C15*$B$9 | F15: =Perfis!A5 | G15: =INDEX(Perfis!$B$4:$D$9,MATCH(F15,Perfis!$A$4:$A$9,0),MATCH($B$10,Perfis!$B$3:$D$3,0)) | H15: =$B$6*G15
A16: 10 | B16: =$B$7+($B$6*A16*12) | C16: =FV($B$9,A16*12,-$B$6,-$B$7,0) | D16: =C16*$B$9 | F16: =Perfis!A6 | G16: =INDEX(Perfis!$B$4:$D$9,MATCH(F16,Perfis!$A$4:$A$9,0),MATCH($B$10,Perfis!$B$3:$D$3,0)) | H16: =$B$6*G16
A17: 20 | B17: =$B$7+($B$6*A17*12) | C17: =FV($B$9,A17*12,-$B$6,-$B$7,0) | D17: =C17*$B$9 | F17: =Perfis!A7 | G17: =INDEX(Perfis!$B$4:$D$9,MATCH(F17,Perfis!$A$4:$A$9,0),MATCH($B$10,Perfis!$B$3:$D$3,0)) | H17: =$B$6*G17
A18: 30 | B18: =$B$7+($B$6*A18*12) | C18: =FV($B$9,A18*12,-$B$6,-$B$7,0) | D18: =C18*$B$9 | F18: =Perfis!A8 | G18: =INDEX(Perfis!$B$4:$D$9,MATCH(F18,Perfis!$A$4:$A$9,0),MATCH($B$10,Perfis!$B$3:$D$3,0)) | H18: =$B$6*G18
F19: =Perfis!A9 | G19: =INDEX(Perfis!$B$4:$D$9,MATCH(F19,Perfis!$A$4:$A$9,0),MATCH($B$10,Perfis!$B$3:$D$3,0)) | H19: =$B$6*G19
A22: EVOLUÇÃO MENSAL DA SIMULAÇÃO
A23: Mês | B23: Aporte Mensal | C23: Total Investido | D23: Patrimônio Acumulado | E23: Rendimento do Mês | F23: Dividendos Estimados
A24: 1 | B24: =IF(A24<=$B$8*12,$B$6,"") | C24: =IF(A24<=$B$8*12,$B$7+B24,"") | D24: =IF(A24<=$B$8*12,($B$7+B24)*(1+$B$9),"") | E24: =IF(A24<=$B$8*12,D24-$B$6-IFERROR(D23,$B$7),"") | F24: =IF(A24<=$B$8*12,D24*$B$9,"")
A25: 2 | B25: =IF(A25<=$B$8*12,$B$6,"") | C25: =IF(A25<=$B$8*12,C24+B25,"") | D25: =IF(A25<=$B$8*12,(D24+B25)*(1+$B$9),"") | E25: =IF(A25<=$B$8*12,D25-$B$6-IFERROR(D24,$B$7),"") | F25: =IF(A25<=$B$8*12,D25*$B$9,"")
A26: 3 | B26: =IF(A26<=$B$8*12,$B$6,"") | C26: =IF(A26<=$B$8*12,C25+B26,"") | D26: =IF(A26<=$B$8*12,(D25+B26)*(1+$B$9),"") | E26: =IF(A26<=$B$8*12,D26-$B$6-IFERROR(D25,$B$7),"") | F26: =IF(A26<=$B$8*12,D26*$B$9,"")
A27: 4 | B27: =IF(A27<=$B$8*12,$B$6,"") | C27: =IF(A27<=$B$8*12,C26+B27,"") | D27: =IF(A27<=$B$8*12,(D26+B27)*(1+$B$9),"") | E27: =IF(A27<=$B$8*12,D27-$B$6-IFERROR(D26,$B$7),"") | F27: =IF(A27<=$B$8*12,D27*$B$9,"")
A28: 5 | B28: =IF(A28<=$B$8*12,$B$6,"") | C28: =IF(A28<=$B$8*12,C27+B28,"") | D28: =IF(A28<=$B$8*12,(D27+B28)*(1+$B$9),"") | E28: =IF(A28<=$B$8*12,D28-$B$6-IFERROR(D27,$B$7),"") | F28: =IF(A28<=$B$8*12,D28*$B$9,"")
A29: 6 | B29: =IF(A29<=$B$8*12,$B$6,"") | C29: =IF(A29<=$B$8*12,C28+B29,"") | D29: =IF(A29<=$B$8*12,(D28+B29)*(1+$B$9),"") | E29: =IF(A29<=$B$8*12,D29-$B$6-IFERROR(D28,$B$7),"") | F29: =IF(A29<=$B$8*12,D29*$B$9,"")
A30: 7 | B30: =IF(A30<=$B$8*12,$B$6,"") | C30: =IF(A30<=$B$8*12,C29+B30,"") | D30: =IF(A30<=$B$8*12,(D29+B30)*(1+$B$9),"") | E30: =IF(A30<=$B$8*12,D30-$B$6-IFERROR(D29,$B$7),"") | F30: =IF(A30<=$B$8*12,D30*$B$9,"")
A31: 8 | B31: =IF(A31<=$B$8*12,$B$6,"") | C31: =IF(A31<=$B$8*12,C30+B31,"") | D31: =IF(A31<=$B$8*12,(D30+B31)*(1+$B$9),"") | E31: =IF(A31<=$B$8*12,D31-$B$6-IFERROR(D30,$B$7),"") | F31: =IF(A31<=$B$8*12,D31*$B$9,"")
A32: 9 | B32: =IF(A32<=$B$8*12,$B$6,"") | C32: =IF(A32<=$B$8*12,C31+B32,"") | D32: =IF(A32<=$B$8*12,(D31+B32)*(1+$B$9),"") | E32: =IF(A32<=$B$8*12,D32-$B$6-IFERROR(D31,$B$7),"") | F32: =IF(A32<=$B$8*12,D32*$B$9,"")
A33: 10 | B33: =IF(A33<=$B$8*12,$B$6,"") | C33: =IF(A33<=$B$8*12,C32+B33,"") | D33: =IF(A33<=$B$8*12,(D32+B33)*(1+$B$9),"") | E33: =IF(A33<=$B$8*12,D33-$B$6-IFERROR(D32,$B$7),"") | F33: =IF(A33<=$B$8*12,D33*$B$9,"")
A34: 11 | B34: =IF(A34<=$B$8*12,$B$6,"") | C34: =IF(A34<=$B$8*12,C33+B34,"") | D34: =IF(A34<=$B$8*12,(D33+B34)*(1+$B$9),"") | E34: =IF(A34<=$B$8*12,D34-$B$6-IFERROR(D33,$B$7),"") | F34: =IF(A34<=$B$8*12,D34*$B$9,"")
A35: 12 | B35: =IF(A35<=$B$8*12,$B$6,"") | C35: =IF(A35<=$B$8*12,C34+B35,"") | D35: =IF(A35<=$B$8*12,(D34+B35)*(1+$B$9),"") | E35: =IF(A35<=$B$8*12,D35-$B$6-IFERROR(D34,$B$7),"") | F35: =IF(A35<=$B$8*12,D35*$B$9,"")
A36: 13 | B36: =IF(A36<=$B$8*12,$B$6,"") | C36: =IF(A36<=$B$8*12,C35+B36,"") | D36: =IF(A36<=$B$8*12,(D35+B36)*(1+$B$9),"") | E36: =IF(A36<=$B$8*12,D36-$B$6-IFERROR(D35,$B$7),"") | F36: =IF(A36<=$B$8*12,D36*$B$9,"")
... A383: 360 | B383: =IF(A383<=$B$8*12,$B$6,"") | C383: =IF(A383<=$B$8*12,C382+B383,"") | D383: =IF(A383<=$B$8*12,(D382+B383)*(1+$B$9),"") | E383: =IF(A383<=$B$8*12,D383-$B$6-IFERROR(D382,$B$7),"") | F383: =IF(A383<=$B$8*12,D383*$B$9,"")

Sheet Perfis
A1: PERFIL DO INVESTIDOR
A3: Tipo de FII | B3: Conservador | C3: Moderado | D3: Agressivo
A4: Papel | B4: 0.35 | C4: 0.3 | D4: 0.2
A5: Tijolo | B5: 0.35 | C5: 0.3 | D5: 0.25
A6: Híbridos | B6: 0.15 | C6: 0.15 | D6: 0.15
A7: FOFs | B7: 0.1 | C7: 0.1 | D7: 0.1
A8: Desenvolvimento | B8: 0.03 | C8: 0.08 | D8: 0.15
A9: Hotelarias | B9: 0.02 | C9: 0.07 | D9: 0.15
A11: TOTAL | B11: =SUM(B4:B9) | C11: =SUM(C4:C9) | D11: =SUM(D4:D9)
